{
    "info": {
        "added": 1626981029.35331, 
        "started": 1627051870.11615, 
        "duration": 73, 
        "ended": 1627051944.033046, 
        "owner": null, 
        "score": 0.0, 
        "id": 2325352, 
        "category": "file", 
        "git": {
            "head": "", 
            "fetch_head": ""
        }, 
        "monitor": null, 
        "package": "elf", 
        "route": "internet", 
        "custom": null, 
        "machine": {
            "status": "stopped", 
            "name": "Ubuntu1904x642", 
            "label": "Ubuntu1904x642", 
            "platform": "linux", 
            "manager": "VirtualBox", 
            "started_on": "2021-07-23 14:51:10", 
            "shutdown_on": "2021-07-23 14:52:23"
        }, 
        "platform": "linux", 
        "version": "2.0.7", 
        "options": "procmemdump=yes,route=internet"
    }, 
    "signatures": [], 
    "target": {
        "category": "file", 
        "file": {
            "mimetype": "application/x-sharedlib", 
            "yara": [], 
            "sha1": "f269299ef5d03f13bbec3ccb28e10a661b76f7b5", 
            "name": "clear_console", 
            "type": "ELF 32-bit LSB shared object, Intel 80386, version 1 (SYSV), dynamically linked, interpreter /lib/ld-linux.so.2, for GNU/Linux 3.2.0, BuildID[sha1]=43600df9b069d4948d09b7ab55e42e2feba149cc, stripped", 
            "sha256": "7f9dcdf6ecf1a793126db8c2f525b4e69ed579d34362ee09303ace1c97416555", 
            "urls": [], 
            "crc32": "B1C9AB04", 
            "path": "/srv/cuckoo/cwd/storage/binaries/7f9dcdf6ecf1a793126db8c2f525b4e69ed579d34362ee09303ace1c97416555", 
            "ssdeep": null, 
            "size": 9628, 
            "sha512": "c7b99a0fed2e099f11edc0d391edc9ae69b3320ad38a8bbbfdd9abe6a2fd2cf62d6bd0ef83aa795e807c59b54c43be2d113469e225c52571b7d656796d1d8e50", 
            "md5": "8f449e4314a0aaf8cebd290967a1d15d"
        }, 
        "custom": null
    }, 
    "irma": {
        "status": 0, 
        "probes_finished": 16, 
        "scan_id": "ca951357-5a8a-45b0-acd9-9a9409713b01", 
        "parent_file_sha256": null, 
        "name": "7f9dcdf6ecf1a793126db8c2f525b4e69ed579d34362ee09303ace1c97416555", 
        "scan_date": 1627074593, 
        "other_results": [], 
        "submitter": "cli", 
        "probes_total": 16, 
        "file_infos": {
            "mimetype": "ELF 32-bit LSB shared object, Intel 80386, version 1 (SYSV)", 
            "sha1": "f269299ef5d03f13bbec3ccb28e10a661b76f7b5", 
            "tags": [], 
            "timestamp_first_scan": 1626880925.39, 
            "timestamp_last_scan": 1627074607.8, 
            "sha256": "7f9dcdf6ecf1a793126db8c2f525b4e69ed579d34362ee09303ace1c97416555", 
            "md5": "8f449e4314a0aaf8cebd290967a1d15d", 
            "size": 9628
        }, 
        "probe_results": {
            "antivirus": {
                "Avast Core Security (Linux)": {
                    "status": 0, 
                    "duration": 0.01, 
                    "version": "3.0.3", 
                    "results": null, 
                    "virus_database_version": "unavailable"
                }, 
                "F-Secure Antivirus (Linux)": {
                    "status": 0, 
                    "duration": 0.02, 
                    "version": "11.10", 
                    "results": null, 
                    "virus_database_version": "2021-06-08_09"
                }, 
                "Windows Defender (Windows)": {
                    "status": 0, 
                    "duration": 0.06, 
                    "version": "1.1.18300.4", 
                    "results": null, 
                    "virus_database_version": "1.343.1173.0"
                }, 
                "Comodo Antivirus (Linux)": {
                    "status": 0, 
                    "duration": 2.18, 
                    "version": "1.1.268025.1", 
                    "results": null, 
                    "virus_database_version": "2021-05-05"
                }, 
                "ESET NOD32 Antivirus (Linux)": {
                    "status": 0, 
                    "duration": 4.14, 
                    "version": "4.0.96", 
                    "results": null, 
                    "virus_database_version": "6087dbf0-1e845 (2021-04-27)"
                }, 
                "GData (Windows)": {
                    "status": 0, 
                    "duration": 0.17, 
                    "version": "5.5.20197.1358", 
                    "results": null, 
                    "virus_database_version": "unavailable"
                }, 
                "Forticlient (Linux)": {
                    "status": -1, 
                    "duration": 3.24, 
                    "version": "unavailable", 
                    "virus_database_version": "unavailable", 
                    "error": "/opt/forticlient/scan.sh: line 8: 1784697 Segmentation fault      (core dumped) \"$scanbin\" -s \"$vir_sig\" -o \"$tmpdir\" --unit \"${forti}/\" -d \"$1\""
                }, 
                "Avira (Windows)": {
                    "status": 0, 
                    "duration": 3.84, 
                    "version": "8.3.62.226", 
                    "results": null, 
                    "virus_database_version": "8.18.36.236"
                }, 
                "Kaspersky (Windows)": {
                    "status": 0, 
                    "duration": 0.61, 
                    "version": "21.3", 
                    "results": null, 
                    "virus_database_version": "2021-07-21 19:18:00 (full)"
                }, 
                "McAfee CLI scanner (Linux)": {
                    "status": 0, 
                    "duration": 5.03, 
                    "version": "6.0.6.653", 
                    "results": null, 
                    "virus_database_version": "9966"
                }, 
                "Sophos Anti-Virus (Linux)": {
                    "status": 0, 
                    "duration": 11.62, 
                    "version": "5.74.0", 
                    "results": null, 
                    "virus_database_version": "5.83 (23 March 2021)"
                }, 
                "DrWeb Antivirus (Linux)": {
                    "status": 0, 
                    "duration": 0.09, 
                    "version": "11.1.9.2103151924", 
                    "results": null, 
                    "virus_database_version": "unavailable"
                }, 
                "ClamAV (Linux)": {
                    "status": 0, 
                    "duration": 0.02, 
                    "version": "0.103.2", 
                    "results": null, 
                    "virus_database_version": "26190"
                }, 
                "eScan Antivirus (Linux)": {
                    "status": 0, 
                    "duration": 4.1, 
                    "version": "7.0.21", 
                    "results": null, 
                    "virus_database_version": "7.88854 (16/06/2021)"
                }, 
                "Emsisoft Commandline Scanner (Windows)": {
                    "status": 0, 
                    "duration": 0.23, 
                    "version": "2021.1.0.10606", 
                    "results": null, 
                    "virus_database_version": "unavailable"
                }, 
                "Bitdefender Antivirus Scanner (Linux)": {
                    "status": 0, 
                    "duration": 5.65, 
                    "version": "7.90123", 
                    "results": null, 
                    "virus_database_version": null
                }
            }
        }, 
        "path": "", 
        "result_id": "550eb927-6d84-46d5-8075-4e9986182ddd", 
        "file_sha256": "7f9dcdf6ecf1a793126db8c2f525b4e69ed579d34362ee09303ace1c97416555"
    }, 
    "suricata": {
        "tls": [
            {
                "src_ip": "192.168.168.102", 
                "version": "TLS 1.2", 
                "src_port": 37704, 
                "dst_port": 443, 
                "timestamp": "2021-07-23T14:51:26.414392+0300", 
                "dst_ip": "91.189.92.19", 
                "fingerprint": "ee:ac:e2:90:ec:e5:1a:a1:dd:74:f7:d4:fa:e8:3e:d9:58:da:e9:25", 
                "subject": "CN=api.snapcraft.io", 
                "issuer": "C=US, O=Let's Encrypt, CN=R3"
            }
        ], 
        "files": [], 
        "alerts": [], 
        "http": []
    }, 
    "virustotal": {
        "scans": {
            "Bkav": {
                "detected": false, 
                "version": "1.3.0.9899", 
                "result": null, 
                "normalized": [], 
                "update": "20210531"
            }, 
            "Lionic": {
                "detected": false, 
                "version": "4.2", 
                "result": null, 
                "normalized": [], 
                "update": "20210601"
            }, 
            "ClamAV": {
                "detected": false, 
                "version": "0.103.2.0", 
                "result": null, 
                "normalized": [], 
                "update": "20210531"
            }, 
            "FireEye": {
                "detected": false, 
                "version": "32.44.1.0", 
                "result": null, 
                "normalized": [], 
                "update": "20210601"
            }, 
            "CAT-QuickHeal": {
                "detected": false, 
                "version": "14.00", 
                "result": null, 
                "normalized": [], 
                "update": "20210531"
            }, 
            "ALYac": {
                "detected": false, 
                "version": "1.1.3.1", 
                "result": null, 
                "normalized": [], 
                "update": "20210601"
            }, 
            "Malwarebytes": {
                "detected": false, 
                "version": "4.2.2.27", 
                "result": null, 
                "normalized": [], 
                "update": "20210601"
            }, 
            "Zillya": {
                "detected": false, 
                "version": "2.0.0.4377", 
                "result": null, 
                "normalized": [], 
                "update": "20210531"
            }, 
            "Sangfor": {
                "detected": false, 
                "version": "2.9.0.0", 
                "result": null, 
                "normalized": [], 
                "update": "20210416"
            }, 
            "K7AntiVirus": {
                "detected": false, 
                "version": "11.185.37311", 
                "result": null, 
                "normalized": [], 
                "update": "20210601"
            }, 
            "K7GW": {
                "detected": false, 
                "version": "11.185.37311", 
                "result": null, 
                "normalized": [], 
                "update": "20210601"
            }, 
            "Arcabit": {
                "detected": false, 
                "version": "1.0.0.886", 
                "result": null, 
                "normalized": [], 
                "update": "20210601"
            }, 
            "BitDefenderTheta": {
                "detected": false, 
                "version": "7.2.37796.0", 
                "result": null, 
                "normalized": [], 
                "update": "20210525"
            }, 
            "Cyren": {
                "detected": false, 
                "version": "6.3.0.2", 
                "result": null, 
                "normalized": [], 
                "update": "20210601"
            }, 
            "Symantec": {
                "detected": false, 
                "version": "1.14.0.0", 
                "result": null, 
                "normalized": [], 
                "update": "20210531"
            }, 
            "ESET-NOD32": {
                "detected": false, 
                "version": "23388", 
                "result": null, 
                "normalized": [], 
                "update": "20210601"
            }, 
            "TrendMicro-HouseCall": {
                "detected": false, 
                "version": "10.0.0.1040", 
                "result": null, 
                "normalized": [], 
                "update": "20210601"
            }, 
            "Avast": {
                "detected": false, 
                "version": "21.1.5827.0", 
                "result": null, 
                "normalized": [], 
                "update": "20210601"
            }, 
            "Cynet": {
                "detected": false, 
                "version": "4.0.0.27", 
                "result": null, 
                "normalized": [], 
                "update": "20210601"
            }, 
            "Kaspersky": {
                "detected": false, 
                "version": "21.0.1.45", 
                "result": null, 
                "normalized": [], 
                "update": "20210601"
            }, 
            "BitDefender": {
                "detected": false, 
                "version": "7.2", 
                "result": null, 
                "normalized": [], 
                "update": "20210601"
            }, 
            "NANO-Antivirus": {
                "detected": false, 
                "version": "1.0.146.25311", 
                "result": null, 
                "normalized": [], 
                "update": "20210531"
            }, 
            "SUPERAntiSpyware": {
                "detected": false, 
                "version": "5.6.0.1032", 
                "result": null, 
                "normalized": [], 
                "update": "20210529"
            }, 
            "MicroWorld-eScan": {
                "detected": false, 
                "version": "14.0.409.0", 
                "result": null, 
                "normalized": [], 
                "update": "20210601"
            }, 
            "Tencent": {
                "detected": false, 
                "version": "1.0.0.1", 
                "result": null, 
                "normalized": [], 
                "update": "20210601"
            }, 
            "Ad-Aware": {
                "detected": false, 
                "version": "3.0.21.179", 
                "result": null, 
                "normalized": [], 
                "update": "20210601"
            }, 
            "Sophos": {
                "detected": false, 
                "version": "1.0.2.0", 
                "result": null, 
                "normalized": [], 
                "update": "20210601"
            }, 
            "Baidu": {
                "detected": false, 
                "version": "1.0.0.2", 
                "result": null, 
                "normalized": [], 
                "update": "20190318"
            }, 
            "F-Secure": {
                "detected": false, 
                "version": "12.0.86.52", 
                "result": null, 
                "normalized": [], 
                "update": "20210601"
            }, 
            "DrWeb": {
                "detected": false, 
                "version": "7.0.49.9080", 
                "result": null, 
                "normalized": [], 
                "update": "20210601"
            }, 
            "VIPRE": {
                "detected": false, 
                "version": "92968", 
                "result": null, 
                "normalized": [], 
                "update": "20210601"
            }, 
            "TrendMicro": {
                "detected": false, 
                "version": "11.0.0.1006", 
                "result": null, 
                "normalized": [], 
                "update": "20210601"
            }, 
            "McAfee-GW-Edition": {
                "detected": false, 
                "version": "v2019.1.2+3728", 
                "result": null, 
                "normalized": [], 
                "update": "20210531"
            }, 
            "CMC": {
                "detected": false, 
                "version": "2.10.2019.1", 
                "result": null, 
                "normalized": [], 
                "update": "20210506"
            }, 
            "Emsisoft": {
                "detected": false, 
                "version": "2018.12.0.1641", 
                "result": null, 
                "normalized": [], 
                "update": "20210601"
            }, 
            "SentinelOne": {
                "detected": false, 
                "version": "5.1.0.5", 
                "result": null, 
                "normalized": [], 
                "update": "20210518"
            }, 
            "Avast-Mobile": {
                "detected": false, 
                "version": "210531-04", 
                "result": null, 
                "normalized": [], 
                "update": "20210531"
            }, 
            "Jiangmin": {
                "detected": false, 
                "version": "16.0.100", 
                "result": null, 
                "normalized": [], 
                "update": "20210530"
            }, 
            "Avira": {
                "detected": false, 
                "version": "8.3.3.12", 
                "result": null, 
                "normalized": [], 
                "update": "20210601"
            }, 
            "Antiy-AVL": {
                "detected": false, 
                "version": "3.0.0.1", 
                "result": null, 
                "normalized": [], 
                "update": "20210601"
            }, 
            "Kingsoft": {
                "detected": false, 
                "version": "2017.9.26.565", 
                "result": null, 
                "normalized": [], 
                "update": "20210601"
            }, 
            "Gridinsoft": {
                "detected": false, 
                "version": "1.0.42.134", 
                "result": null, 
                "normalized": [], 
                "update": "20210601"
            }, 
            "Microsoft": {
                "detected": false, 
                "version": "1.1.18200.4", 
                "result": null, 
                "normalized": [], 
                "update": "20210601"
            }, 
            "ViRobot": {
                "detected": false, 
                "version": "2014.3.20.0", 
                "result": null, 
                "normalized": [], 
                "update": "20210601"
            }, 
            "ZoneAlarm": {
                "detected": false, 
                "version": "1.0", 
                "result": null, 
                "normalized": [], 
                "update": "20210601"
            }, 
            "GData": {
                "detected": false, 
                "version": "A:25.29823B:27.23206", 
                "result": null, 
                "normalized": [], 
                "update": "20210601"
            }, 
            "TACHYON": {
                "detected": false, 
                "version": "2021-06-01.01", 
                "result": null, 
                "normalized": [], 
                "update": "20210601"
            }, 
            "AhnLab-V3": {
                "detected": false, 
                "version": "3.20.1.10133", 
                "result": null, 
                "normalized": [], 
                "update": "20210531"
            }, 
            "Acronis": {
                "detected": false, 
                "version": "1.1.1.82", 
                "result": null, 
                "normalized": [], 
                "update": "20210512"
            }, 
            "McAfee": {
                "detected": false, 
                "version": "6.0.6.653", 
                "result": null, 
                "normalized": [], 
                "update": "20210601"
            }, 
            "MAX": {
                "detected": false, 
                "version": "2019.9.16.1", 
                "result": null, 
                "normalized": [], 
                "update": "20210601"
            }, 
            "VBA32": {
                "detected": false, 
                "version": "5.0.0", 
                "result": null, 
                "normalized": [], 
                "update": "20210531"
            }, 
            "Zoner": {
                "detected": false, 
                "version": "0.0.0.0", 
                "result": null, 
                "normalized": [], 
                "update": "20210531"
            }, 
            "Rising": {
                "detected": false, 
                "version": "25.0.0.26", 
                "result": null, 
                "normalized": [], 
                "update": "20210531"
            }, 
            "Yandex": {
                "detected": false, 
                "version": "5.5.2.24", 
                "result": null, 
                "normalized": [], 
                "update": "20210529"
            }, 
            "Ikarus": {
                "detected": false, 
                "version": "0.1.5.2", 
                "result": null, 
                "normalized": [], 
                "update": "20210531"
            }, 
            "MaxSecure": {
                "detected": false, 
                "version": "1.0.0.1", 
                "result": null, 
                "normalized": [], 
                "update": "20210531"
            }, 
            "Fortinet": {
                "detected": false, 
                "version": "6.2.142.0", 
                "result": null, 
                "normalized": [], 
                "update": "20210601"
            }, 
            "Panda": {
                "detected": false, 
                "version": "4.6.4.2", 
                "result": null, 
                "normalized": [], 
                "update": "20210531"
            }, 
            "Qihoo-360": {
                "detected": false, 
                "version": "1.0.0.1120", 
                "result": null, 
                "normalized": [], 
                "update": "20210601"
            }
        }, 
        "scan_id": "7f9dcdf6ecf1a793126db8c2f525b4e69ed579d34362ee09303ace1c97416555-1622524422", 
        "sha1": "f269299ef5d03f13bbec3ccb28e10a661b76f7b5", 
        "resource": "8f449e4314a0aaf8cebd290967a1d15d", 
        "response_code": 1, 
        "scan_date": "2021-06-01 05:13:42", 
        "permalink": "https://www.virustotal.com/gui/file/7f9dcdf6ecf1a793126db8c2f525b4e69ed579d34362ee09303ace1c97416555/detection/f-7f9dcdf6ecf1a793126db8c2f525b4e69ed579d34362ee09303ace1c97416555-1622524422", 
        "summary": {
            "positives": 0, 
            "permalink": "https://www.virustotal.com/gui/file/7f9dcdf6ecf1a793126db8c2f525b4e69ed579d34362ee09303ace1c97416555/detection/f-7f9dcdf6ecf1a793126db8c2f525b4e69ed579d34362ee09303ace1c97416555-1622524422", 
            "scan_date": "2021-06-01 05:13:42"
        }, 
        "sha256": "7f9dcdf6ecf1a793126db8c2f525b4e69ed579d34362ee09303ace1c97416555", 
        "normalized": [], 
        "total": 60, 
        "positives": 0, 
        "verbose_msg": "Scan finished, information embedded", 
        "md5": "8f449e4314a0aaf8cebd290967a1d15d"
    }, 
    "network": {
        "udp": [], 
        "dns_servers": [], 
        "http": [], 
        "smtp": [], 
        "tcp": [], 
        "geoinfo": {}, 
        "mitm": [], 
        "https_ex": [], 
        "http_ex": [], 
        "sorted_pcap_sha256": "17589d49bdec9209414275f8dde694392eb7199c30b9a8fd9309d7910cdf971f", 
        "icmp": [], 
        "tls": [], 
        "dead_hosts": [], 
        "smtp_ex": [], 
        "hosts": [], 
        "pcap_sha256": "33eb29e55beb5b530012f85d1373c92a08399d420953fafb53e49a47339ed65f", 
        "dns": [], 
        "domains": [], 
        "irc": []
    }, 
    "resubmit": {
        "resubmit_ids": []
    }, 
    "snort": {
        "alerts": []
    }, 
    "behavior": {
        "generic": [
            {
                "process_path": null, 
                "process_name": "sh", 
                "pid": 2077, 
                "summary": {}, 
                "first_seen": 1626981035.776166, 
                "ppid": -1
            }
        ], 
        "processes": [
            {
                "calls": [
                    {
                        "status": "ENOENT", 
                        "process_name": "sh", 
                        "pid": 2077, 
                        "raw": "Thu Jul 22 19:10:35 2021.776166 sh@7f7907706957[2077] execve(\"/tmp/clear_console\", [\"/tmp/clear_console\"], [\"SUDO_GID=0\", \"MAIL=/var/mail/root\", \"USER=root\", \"HOME=/root\", \"SUDO_UID=0\", \"LOGNAME=root\", \"SYSTEMTAP_MODULE=stap_\", \"TERM=unknown\", \"SYSTEMTAP_VERBOSE=2\", \"PATH=/usr/local/sbin:/usr/local/bin:/usr/sbin:/usr/bin:/sbin:/bin:/snap/bin\", \"DISPLAY=:0\", \"LANG=en_US.UTF-8\", \"XAUTHORITY=/root/.Xauthority\", \"SUDO_COMMAND=/usr/bin/staprun -vv -o stap.log /root/.cuckoo/stap_.ko -c sh -c /tmp/clear_console\", \"SHELL=/bin/bash\", \"SUDO_USER=root\", \"PWD=/tmp/tmpwbvE1K\"]) = -2 (ENOENT)\n", 
                        "api": "execve", 
                        "return_value": "-2", 
                        "category": "process", 
                        "instruction_pointer": "7f7907706957", 
                        "arguments": {
                            "p2": [
                                "SUDO_GID=0", 
                                "MAIL=/var/mail/root", 
                                "USER=root", 
                                "HOME=/root", 
                                "SUDO_UID=0", 
                                "LOGNAME=root", 
                                "SYSTEMTAP_MODULE=stap_", 
                                "TERM=unknown", 
                                "SYSTEMTAP_VERBOSE=2", 
                                "PATH=/usr/local/sbin:/usr/local/bin:/usr/sbin:/usr/bin:/sbin:/bin:/snap/bin", 
                                "DISPLAY=:0", 
                                "LANG=en_US.UTF-8", 
                                "XAUTHORITY=/root/.Xauthority", 
                                "SUDO_COMMAND=/usr/bin/staprun -vv -o stap.log /root/.cuckoo/stap_.ko -c sh -c /tmp/clear_console", 
                                "SHELL=/bin/bash", 
                                "SUDO_USER=root", 
                                "PWD=/tmp/tmpwbvE1K"
                            ], 
                            "p0": "/tmp/clear_console", 
                            "p1": [
                                "/tmp/clear_console"
                            ]
                        }, 
                        "time": 1626981035.776166
                    }, 
                    {
                        "status": "", 
                        "process_name": "sh", 
                        "pid": 2077, 
                        "raw": "Thu Jul 22 19:10:35 2021.776304 sh@7f7907732024[2077] write(2, \"sh: 1: \", 7) = 7\n", 
                        "api": "write", 
                        "return_value": "7", 
                        "category": "process", 
                        "instruction_pointer": "7f7907732024", 
                        "arguments": {
                            "p2": "7", 
                            "p0": "2", 
                            "p1": "sh: 1: "
                        }, 
                        "time": 1626981035.776304
                    }, 
                    {
                        "status": "", 
                        "process_name": "sh", 
                        "pid": 2077, 
                        "raw": "Thu Jul 22 19:10:35 2021.776383 sh@7f7907732024[2077] write(2, \"/tmp/clear_console: not found\", 29) = 29\n", 
                        "api": "write", 
                        "return_value": "29", 
                        "category": "process", 
                        "instruction_pointer": "7f7907732024", 
                        "arguments": {
                            "p2": "29", 
                            "p0": "2", 
                            "p1": "/tmp/clear_console: not found"
                        }, 
                        "time": 1626981035.776383
                    }, 
                    {
                        "status": "", 
                        "process_name": "sh", 
                        "pid": 2077, 
                        "raw": "Thu Jul 22 19:10:35 2021.776444 sh@7f7907732024[2077] write(2, \"\\n\", 1) = 1\n", 
                        "api": "write", 
                        "return_value": "1", 
                        "category": "process", 
                        "instruction_pointer": "7f7907732024", 
                        "arguments": {
                            "p2": "1", 
                            "p0": "2", 
                            "p1": "\n"
                        }, 
                        "time": 1626981035.776444
                    }, 
                    {
                        "status": "", 
                        "process_name": "sh", 
                        "pid": 2077, 
                        "raw": "Thu Jul 22 19:10:35 2021.776494 sh@7f7907706926[2077] exit_group(127)\n", 
                        "api": "exit_group", 
                        "return_value": "", 
                        "category": "process", 
                        "instruction_pointer": "7f7907706926", 
                        "arguments": {
                            "p0": "127"
                        }, 
                        "time": 1626981035.776494
                    }
                ], 
                "pid": 2077, 
                "process_name": "sh", 
                "command_line": "", 
                "first_seen": 1626981035.776166, 
                "ppid": -1, 
                "type": "process"
            }
        ], 
        "processtree": [
            {
                "track": true, 
                "pid": 2077, 
                "process_name": "sh", 
                "command_line": "", 
                "first_seen": 1626981035.776166, 
                "ppid": -1, 
                "children": []
            }
        ]
    }, 
    "debug": {
        "action": [], 
        "dbgview": [], 
        "errors": [], 
        "log": [
            "2021-07-22 19:10:29,007 [root] DEBUG: Starting analyzer from: /tmp/tmpwbvE1K\n", 
            "2021-07-22 19:10:29,007 [root] DEBUG: Storing results at: /tmp/uarMGnAqN\n", 
            "2021-07-22 19:10:30,461 [modules.auxiliary.filecollector] INFO: FileCollector started v0.08\n", 
            "2021-07-22 19:10:30,463 [modules.auxiliary.human] INFO: Human started v0.02\n", 
            "2021-07-22 19:10:30,465 [modules.auxiliary.screenshots] INFO: Screenshots started v0.03\n", 
            "2021-07-22 19:10:35,775 [lib.core.packages] INFO: Process startup took 5.30 seconds\n", 
            "2021-07-22 19:10:35,779 [root] INFO: Added new process to list with pid: 2067\n", 
            "2021-07-22 19:10:41,789 [root] INFO: Process with pid 2067 has terminated\n", 
            "2021-07-22 19:10:41,790 [root] INFO: Process list is empty, terminating analysis.\n", 
            "2021-07-22 19:10:44,794 [lib.core.packages] INFO: Package requested stop\n", 
            "2021-07-22 19:10:44,795 [lib.core.packages] WARNING: Exception uploading log: [Errno 3] No such process\n"
        ], 
        "cuckoo": [
            "2021-07-23 14:51:10,640 [cuckoo.core.scheduler] INFO: Task #2325352: acquired machine Ubuntu1904x642 (label=Ubuntu1904x642)\n", 
            "2021-07-23 14:51:10,641 [cuckoo.core.resultserver] DEBUG: Now tracking machine 192.168.168.102 for task #2325352\n", 
            "2021-07-23 14:51:10,779 [cuckoo.auxiliary.sniffer] INFO: Started sniffer with PID 3617799 (interface=vboxnet0, host=192.168.168.102)\n", 
            "2021-07-23 14:51:10,908 [cuckoo.machinery.virtualbox] DEBUG: Starting vm Ubuntu1904x642\n", 
            "2021-07-23 14:51:11,279 [cuckoo.machinery.virtualbox] DEBUG: Restoring virtual machine Ubuntu1904x642 to Snapshot\n", 
            "2021-07-23 14:51:19,904 [cuckoo.core.guest] INFO: Starting analysis #2325352 on guest (id=Ubuntu1904x642, ip=192.168.168.102)\n", 
            "2021-07-23 14:51:20,909 [cuckoo.core.guest] DEBUG: Ubuntu1904x642: not ready yet\n", 
            "2021-07-23 14:51:21,916 [cuckoo.core.guest] DEBUG: Ubuntu1904x642: not ready yet\n", 
            "2021-07-23 14:51:22,923 [cuckoo.core.guest] DEBUG: Ubuntu1904x642: not ready yet\n", 
            "2021-07-23 14:51:22,971 [cuckoo.core.guest] DEBUG: Ubuntu1904x642: not ready yet\n", 
            "2021-07-23 14:51:25,989 [cuckoo.core.guest] INFO: Guest is running Cuckoo Agent 0.10 (id=Ubuntu1904x642, ip=192.168.168.102)\n", 
            "2021-07-23 14:51:26,007 [cuckoo.core.guest] DEBUG: Uploading analyzer to guest (id=Ubuntu1904x642, ip=192.168.168.102, monitor=latest, size=70098)\n", 
            "2021-07-23 14:51:26,158 [cuckoo.core.resultserver] DEBUG: Task #2325352: live log analysis.log initialized.\n", 
            "2021-07-23 14:51:30,814 [cuckoo.core.resultserver] DEBUG: Task #2325352: File upload for 'shots/0001.jpg'\n", 
            "2021-07-23 14:51:30,826 [cuckoo.core.resultserver] DEBUG: Task #2325352 uploaded file length: 171505\n", 
            "2021-07-23 14:51:41,159 [cuckoo.core.guest] DEBUG: Ubuntu1904x642: analysis #2325352 still processing\n", 
            "2021-07-23 14:51:41,958 [cuckoo.core.resultserver] DEBUG: Task #2325352: File upload for 'logs/all.stap'\n", 
            "2021-07-23 14:51:41,961 [cuckoo.core.resultserver] DEBUG: Task #2325352 uploaded file length: 918\n", 
            "2021-07-23 14:51:56,224 [cuckoo.core.guest] DEBUG: Ubuntu1904x642: analysis #2325352 still processing\n", 
            "2021-07-23 14:52:08,274 [cuckoo.core.guest] INFO: Ubuntu1904x642: end of analysis reached!\n", 
            "2021-07-23 14:52:08,283 [cuckoo.core.plugins] DEBUG: Stopped auxiliary module: Redsocks\n", 
            "2021-07-23 14:52:08,343 [cuckoo.core.plugins] DEBUG: Stopped auxiliary module: Sniffer\n", 
            "2021-07-23 14:52:19,839 [cuckoo.machinery.virtualbox] INFO: Successfully generated memory dump for virtual machine with label Ubuntu1904x642 to path /srv/cuckoo/cwd/storage/analyses/2325352/memory.dmp\n", 
            "2021-07-23 14:52:19,840 [cuckoo.machinery.virtualbox] DEBUG: Stopping vm Ubuntu1904x642\n", 
            "2021-07-23 14:52:23,667 [cuckoo.core.resultserver] DEBUG: Stopped tracking machine 192.168.168.102 for task #2325352\n", 
            "2021-07-23 14:52:23,668 [cuckoo.core.resultserver] DEBUG: Cancel <Context for LOG> for task 2325352\n", 
            "2021-07-23 14:52:23,793 [cuckoo.core.scheduler] DEBUG: Released database task #2325352\n", 
            "2021-07-23 14:52:23,901 [cuckoo.core.scheduler] INFO: Task #2325352: analysis procedure completed\n"
        ]
    }, 
    "strings": [
        "/lib/ld-linux.so.2", 
        "libtinfo.so.5", 
        "_ITM_deregisterTMCloneTable", 
        "__gmon_start__", 
        "_ITM_registerTMCloneTable", 
        "setupterm", 
        "cur_term", 
        "libc.so.6", 
        "_IO_stdin_used", 
        "_IO_putc", 
        "optind", 
        "strrchr", 
        "perror", 
        "strlen", 
        "__errno_location", 
        "ttyname", 
        "__fprintf_chk", 
        "stdout", 
        "getenv", 
        "stderr", 
        "getopt_long", 
        "fwrite", 
        "__cxa_finalize", 
        "__libc_start_main", 
        "__stack_chk_fail", 
        "progname", 
        "_fp_hw", 
        "GLIBC_2.3.4", 
        "GLIBC_2.1.3", 
        "GLIBC_2.4", 
        "GLIBC_2.0", 
        "NCURSES_TINFO_5.0.19991023", 
        "Usage: %s [option]", 
        "valid options are:", 
        "/dev/tty", 
        "/dev/tty0", 
        "/dev/console", 
        "ttyname", 
        "/dev/pts/", 
        "screen", 
        "%s: cannot get VTstate", 
        "chvt: VT_ACTIVATE", 
        "VT_WAITACTIVE", 
        "%s: Version %s", 
        "version", 
        "-q  --quiet    don't print error messages", 
        "-h --help      display this help text and exit", 
        "-V --version   display version information and exit", 
        "%s: no non-option arguments are valid", 
        "%s: terminal is not a console", 
        "600df9b069d4948d09b7ab55e42e2feba149cc.debug", 
        ".shstrtab", 
        ".interp", 
        ".note.ABI-tag", 
        ".note.gnu.build-id", 
        ".gnu.hash", 
        ".dynsym", 
        ".dynstr", 
        ".gnu.version", 
        ".gnu.version_r", 
        ".rel.dyn", 
        ".rel.plt", 
        ".plt.got", 
        ".rodata", 
        ".eh_frame_hdr", 
        ".eh_frame", 
        ".init_array", 
        ".fini_array", 
        ".data.rel.ro", 
        ".dynamic", 
        ".gnu_debuglink"
    ], 
    "metadata": {
        "output": {
            "pcap": {
                "basename": "dump.pcap", 
                "sha256": "33eb29e55beb5b530012f85d1373c92a08399d420953fafb53e49a47339ed65f", 
                "dirname": ""
            }
        }
    }
}