{
    "info": {
        "added": 1628114317.09971, 
        "started": 1628119549.617005, 
        "duration": 492, 
        "ended": 1628120042.273237, 
        "owner": null, 
        "score": 0.0, 
        "id": 2344785, 
        "category": "file", 
        "git": {
            "head": "", 
            "fetch_head": ""
        }, 
        "monitor": null, 
        "package": "elf", 
        "route": "internet", 
        "custom": null, 
        "machine": {
            "status": "stopped", 
            "name": "win7x6421", 
            "label": "win7x6421", 
            "platform": "windows", 
            "manager": "VirtualBox", 
            "started_on": "2021-08-04 23:26:00", 
            "shutdown_on": "2021-08-04 23:34:00"
        }, 
        "platform": "windows", 
        "version": "2.0.7", 
        "options": "procmemdump=yes,route=internet"
    }, 
    "signatures": [], 
    "target": {
        "category": "file", 
        "file": {
            "mimetype": "application/x-executable", 
            "yara": [], 
            "sha1": "a596f17ef736c4a181d36cc5ccbf564cd220f40d", 
            "name": "rawtoppm", 
            "type": "ELF 32-bit LSB executable, Intel 80386, version 1 (SYSV), dynamically linked, interpreter /lib/ld-linux.so.2, for GNU/Linux 2.6.32, BuildID[sha1]=e7bbb6db289f9fd96d93b8875e733135b9f81e5a, stripped", 
            "sha256": "6d98cbeb6ef546278abd793a04d33f6a3ce2887292b8d6ba03b74622d41db8c5", 
            "urls": [], 
            "crc32": "DBA162EF", 
            "path": "/srv/cuckoo/cwd/storage/binaries/6d98cbeb6ef546278abd793a04d33f6a3ce2887292b8d6ba03b74622d41db8c5", 
            "ssdeep": null, 
            "size": 9628, 
            "sha512": "2f40a77c03a84066db38c858f46cdb815fcaf21b2926e32851cefe6df40cc26b803f585b5b1a776421f53a5ce3653fcb719740c0d8649b315597fb1ddf7ab392", 
            "md5": "07777bbc3ece5d962578c05ffef39764"
        }, 
        "custom": null
    }, 
    "irma": {
        "status": 0, 
        "probes_finished": 16, 
        "scan_id": "978a4038-8c0f-48c7-8aaa-51c201927ba4", 
        "parent_file_sha256": null, 
        "name": "6d98cbeb6ef546278abd793a04d33f6a3ce2887292b8d6ba03b74622d41db8c5", 
        "scan_date": 1628109257, 
        "other_results": [], 
        "submitter": "cli", 
        "probes_total": 16, 
        "file_infos": {
            "mimetype": "ELF 32-bit LSB executable, Intel 80386, version 1 (SYSV)", 
            "sha1": "a596f17ef736c4a181d36cc5ccbf564cd220f40d", 
            "tags": [], 
            "timestamp_first_scan": 1626894849.48, 
            "timestamp_last_scan": 1628109267.8, 
            "sha256": "6d98cbeb6ef546278abd793a04d33f6a3ce2887292b8d6ba03b74622d41db8c5", 
            "md5": "07777bbc3ece5d962578c05ffef39764", 
            "size": 9628
        }, 
        "probe_results": {
            "antivirus": {
                "Avast Core Security (Linux)": {
                    "status": 0, 
                    "duration": 0.01, 
                    "version": "3.0.3", 
                    "results": null, 
                    "virus_database_version": "unavailable"
                }, 
                "F-Secure Antivirus (Linux)": {
                    "status": 0, 
                    "duration": 0.03, 
                    "version": "11.10", 
                    "results": null, 
                    "virus_database_version": "2021-07-22_04"
                }, 
                "Windows Defender (Windows)": {
                    "status": 0, 
                    "duration": 0.03, 
                    "version": "1.1.18300.4", 
                    "results": null, 
                    "virus_database_version": "1.343.1173.0"
                }, 
                "Comodo Antivirus (Linux)": {
                    "status": 0, 
                    "duration": 2.9, 
                    "version": "1.1.268025.1", 
                    "results": null, 
                    "virus_database_version": "2021-05-05"
                }, 
                "ESET NOD32 Antivirus (Linux)": {
                    "status": 0, 
                    "duration": 3.92, 
                    "version": "4.0.96", 
                    "results": null, 
                    "virus_database_version": "6087dbf0-1e845 (2021-04-27)"
                }, 
                "GData (Windows)": {
                    "status": 0, 
                    "duration": 0.16, 
                    "version": "5.5.20197.1358", 
                    "results": null, 
                    "virus_database_version": "unavailable"
                }, 
                "Forticlient (Linux)": {
                    "status": 0, 
                    "duration": 3.02, 
                    "version": "unavailable", 
                    "results": null, 
                    "virus_database_version": "unavailable"
                }, 
                "Avira (Windows)": {
                    "status": 0, 
                    "duration": 4.09, 
                    "version": "8.3.62.226", 
                    "results": null, 
                    "virus_database_version": "8.18.36.236"
                }, 
                "Kaspersky (Windows)": {
                    "status": 0, 
                    "duration": 0.64, 
                    "version": "21.3", 
                    "results": null, 
                    "virus_database_version": "2021-08-03 04:06:00 (full)"
                }, 
                "McAfee CLI scanner (Linux)": {
                    "status": 0, 
                    "duration": 5.05, 
                    "version": "6.0.6.653", 
                    "results": null, 
                    "virus_database_version": "9966"
                }, 
                "Sophos Anti-Virus (Linux)": {
                    "status": 0, 
                    "duration": 7.7, 
                    "version": "5.74.0", 
                    "results": null, 
                    "virus_database_version": "5.83 (23 March 2021)"
                }, 
                "DrWeb Antivirus (Linux)": {
                    "status": 0, 
                    "duration": 0.07, 
                    "version": "11.1.9.2103151924", 
                    "results": null, 
                    "virus_database_version": "unavailable"
                }, 
                "ClamAV (Linux)": {
                    "status": 0, 
                    "duration": 0.02, 
                    "version": "0.103.2", 
                    "results": null, 
                    "virus_database_version": "26190"
                }, 
                "eScan Antivirus (Linux)": {
                    "status": 0, 
                    "duration": 4.0, 
                    "version": "7.0.21", 
                    "results": null, 
                    "virus_database_version": "7.88854 (16/06/2021)"
                }, 
                "Emsisoft Commandline Scanner (Windows)": {
                    "status": 0, 
                    "duration": 0.25, 
                    "version": "2021.1.0.10606", 
                    "results": null, 
                    "virus_database_version": "unavailable"
                }, 
                "Bitdefender Antivirus Scanner (Linux)": {
                    "status": 0, 
                    "duration": 5.6, 
                    "version": "7.90123", 
                    "results": null, 
                    "virus_database_version": null
                }
            }
        }, 
        "path": "", 
        "result_id": "cf6e5327-e9c4-4ccd-a30c-a935f1415440", 
        "file_sha256": "6d98cbeb6ef546278abd793a04d33f6a3ce2887292b8d6ba03b74622d41db8c5"
    }, 
    "suricata": {
        "tls": [], 
        "files": [], 
        "alerts": [], 
        "http": []
    }, 
    "virustotal": {
        "scans": {
            "Bkav": {
                "detected": false, 
                "version": "1.3.0.9899", 
                "result": null, 
                "normalized": [], 
                "update": "20210525"
            }, 
            "Lionic": {
                "detected": false, 
                "version": "4.2", 
                "result": null, 
                "normalized": [], 
                "update": "20210526"
            }, 
            "DrWeb": {
                "detected": false, 
                "version": "7.0.49.9080", 
                "result": null, 
                "normalized": [], 
                "update": "20210526"
            }, 
            "ClamAV": {
                "detected": false, 
                "version": "0.103.2.0", 
                "result": null, 
                "normalized": [], 
                "update": "20210525"
            }, 
            "FireEye": {
                "detected": false, 
                "version": "32.44.1.0", 
                "result": null, 
                "normalized": [], 
                "update": "20210526"
            }, 
            "CAT-QuickHeal": {
                "detected": false, 
                "version": "14.00", 
                "result": null, 
                "normalized": [], 
                "update": "20210525"
            }, 
            "McAfee": {
                "detected": false, 
                "version": "6.0.6.653", 
                "result": null, 
                "normalized": [], 
                "update": "20210504"
            }, 
            "Malwarebytes": {
                "detected": false, 
                "version": "4.2.2.27", 
                "result": null, 
                "normalized": [], 
                "update": "20210526"
            }, 
            "Zillya": {
                "detected": false, 
                "version": "2.0.0.4373", 
                "result": null, 
                "normalized": [], 
                "update": "20210525"
            }, 
            "Sangfor": {
                "detected": false, 
                "version": "2.9.0.0", 
                "result": null, 
                "normalized": [], 
                "update": "20210416"
            }, 
            "K7AntiVirus": {
                "detected": false, 
                "version": "11.184.37278", 
                "result": null, 
                "normalized": [], 
                "update": "20210526"
            }, 
            "K7GW": {
                "detected": false, 
                "version": "11.184.37278", 
                "result": null, 
                "normalized": [], 
                "update": "20210526"
            }, 
            "BitDefenderTheta": {
                "detected": false, 
                "version": "7.2.37796.0", 
                "result": null, 
                "normalized": [], 
                "update": "20210525"
            }, 
            "Cyren": {
                "detected": false, 
                "version": "6.3.0.2", 
                "result": null, 
                "normalized": [], 
                "update": "20210526"
            }, 
            "Symantec": {
                "detected": false, 
                "version": "1.14.0.0", 
                "result": null, 
                "normalized": [], 
                "update": "20210526"
            }, 
            "ESET-NOD32": {
                "detected": false, 
                "version": "23357", 
                "result": null, 
                "normalized": [], 
                "update": "20210526"
            }, 
            "TrendMicro-HouseCall": {
                "detected": false, 
                "version": "10.0.0.1040", 
                "result": null, 
                "normalized": [], 
                "update": "20210526"
            }, 
            "Avast": {
                "detected": false, 
                "version": "21.1.5827.0", 
                "result": null, 
                "normalized": [], 
                "update": "20210526"
            }, 
            "Cynet": {
                "detected": false, 
                "version": "4.0.0.27", 
                "result": null, 
                "normalized": [], 
                "update": "20210526"
            }, 
            "Kaspersky": {
                "detected": false, 
                "version": "21.0.1.45", 
                "result": null, 
                "normalized": [], 
                "update": "20210526"
            }, 
            "BitDefender": {
                "detected": false, 
                "version": "7.2", 
                "result": null, 
                "normalized": [], 
                "update": "20210526"
            }, 
            "NANO-Antivirus": {
                "detected": false, 
                "version": "1.0.146.25311", 
                "result": null, 
                "normalized": [], 
                "update": "20210526"
            }, 
            "SUPERAntiSpyware": {
                "detected": false, 
                "version": "5.6.0.1032", 
                "result": null, 
                "normalized": [], 
                "update": "20210522"
            }, 
            "MicroWorld-eScan": {
                "detected": false, 
                "version": "14.0.409.0", 
                "result": null, 
                "normalized": [], 
                "update": "20210526"
            }, 
            "Tencent": {
                "detected": false, 
                "version": "1.0.0.1", 
                "result": null, 
                "normalized": [], 
                "update": "20210526"
            }, 
            "Ad-Aware": {
                "detected": false, 
                "version": "3.0.21.179", 
                "result": null, 
                "normalized": [], 
                "update": "20210526"
            }, 
            "Emsisoft": {
                "detected": false, 
                "version": "2018.12.0.1641", 
                "result": null, 
                "normalized": [], 
                "update": "20210526"
            }, 
            "Comodo": {
                "detected": false, 
                "version": "33563", 
                "result": null, 
                "normalized": [], 
                "update": "20210526"
            }, 
            "F-Secure": {
                "detected": false, 
                "version": "12.0.86.52", 
                "result": null, 
                "normalized": [], 
                "update": "20210526"
            }, 
            "Baidu": {
                "detected": false, 
                "version": "1.0.0.2", 
                "result": null, 
                "normalized": [], 
                "update": "20190318"
            }, 
            "VIPRE": {
                "detected": false, 
                "version": "92826", 
                "result": null, 
                "normalized": [], 
                "update": "20210526"
            }, 
            "TrendMicro": {
                "detected": false, 
                "version": "11.0.0.1006", 
                "result": null, 
                "normalized": [], 
                "update": "20210526"
            }, 
            "McAfee-GW-Edition": {
                "detected": false, 
                "version": "v2019.1.2+3728", 
                "result": null, 
                "normalized": [], 
                "update": "20210526"
            }, 
            "CMC": {
                "detected": false, 
                "version": "2.10.2019.1", 
                "result": null, 
                "normalized": [], 
                "update": "20210506"
            }, 
            "Sophos": {
                "detected": false, 
                "version": "1.0.2.0", 
                "result": null, 
                "normalized": [], 
                "update": "20210526"
            }, 
            "Avast-Mobile": {
                "detected": false, 
                "version": "210525-02", 
                "result": null, 
                "normalized": [], 
                "update": "20210525"
            }, 
            "Jiangmin": {
                "detected": false, 
                "version": "16.0.100", 
                "result": null, 
                "normalized": [], 
                "update": "20210525"
            }, 
            "Avira": {
                "detected": false, 
                "version": "8.3.3.12", 
                "result": null, 
                "normalized": [], 
                "update": "20210526"
            }, 
            "MAX": {
                "detected": false, 
                "version": "2019.9.16.1", 
                "result": null, 
                "normalized": [], 
                "update": "20210526"
            }, 
            "Antiy-AVL": {
                "detected": false, 
                "version": "3.0.0.1", 
                "result": null, 
                "normalized": [], 
                "update": "20210526"
            }, 
            "Kingsoft": {
                "detected": false, 
                "version": "2017.9.26.565", 
                "result": null, 
                "normalized": [], 
                "update": "20210526"
            }, 
            "Microsoft": {
                "detected": false, 
                "version": "1.1.18200.3", 
                "result": null, 
                "normalized": [], 
                "update": "20210526"
            }, 
            "Gridinsoft": {
                "detected": false, 
                "version": "1.0.41.133", 
                "result": null, 
                "normalized": [], 
                "update": "20210526"
            }, 
            "Arcabit": {
                "detected": false, 
                "version": "1.0.0.886", 
                "result": null, 
                "normalized": [], 
                "update": "20210526"
            }, 
            "ViRobot": {
                "detected": false, 
                "version": "2014.3.20.0", 
                "result": null, 
                "normalized": [], 
                "update": "20210526"
            }, 
            "ZoneAlarm": {
                "detected": false, 
                "version": "1.0", 
                "result": null, 
                "normalized": [], 
                "update": "20210526"
            }, 
            "GData": {
                "detected": false, 
                "version": "A:25.29765B:27.23142", 
                "result": null, 
                "normalized": [], 
                "update": "20210526"
            }, 
            "AhnLab-V3": {
                "detected": false, 
                "version": "3.20.1.10133", 
                "result": null, 
                "normalized": [], 
                "update": "20210526"
            }, 
            "Acronis": {
                "detected": false, 
                "version": "1.1.1.82", 
                "result": null, 
                "normalized": [], 
                "update": "20210512"
            }, 
            "VBA32": {
                "detected": false, 
                "version": "5.0.0", 
                "result": null, 
                "normalized": [], 
                "update": "20210525"
            }, 
            "ALYac": {
                "detected": false, 
                "version": "1.1.3.1", 
                "result": null, 
                "normalized": [], 
                "update": "20210526"
            }, 
            "TACHYON": {
                "detected": false, 
                "version": "2021-05-26.01", 
                "result": null, 
                "normalized": [], 
                "update": "20210526"
            }, 
            "Zoner": {
                "detected": false, 
                "version": "0.0.0.0", 
                "result": null, 
                "normalized": [], 
                "update": "20210525"
            }, 
            "Rising": {
                "detected": false, 
                "version": "25.0.0.26", 
                "result": null, 
                "normalized": [], 
                "update": "20210526"
            }, 
            "Yandex": {
                "detected": false, 
                "version": "5.5.2.24", 
                "result": null, 
                "normalized": [], 
                "update": "20210525"
            }, 
            "SentinelOne": {
                "detected": false, 
                "version": "5.1.0.5", 
                "result": null, 
                "normalized": [], 
                "update": "20210518"
            }, 
            "MaxSecure": {
                "detected": false, 
                "version": "1.0.0.1", 
                "result": null, 
                "normalized": [], 
                "update": "20210525"
            }, 
            "Fortinet": {
                "detected": false, 
                "version": "6.2.142.0", 
                "result": null, 
                "normalized": [], 
                "update": "20210526"
            }, 
            "Panda": {
                "detected": false, 
                "version": "4.6.4.2", 
                "result": null, 
                "normalized": [], 
                "update": "20210525"
            }, 
            "Qihoo-360": {
                "detected": false, 
                "version": "1.0.0.1120", 
                "result": null, 
                "normalized": [], 
                "update": "20210526"
            }
        }, 
        "scan_id": "6d98cbeb6ef546278abd793a04d33f6a3ce2887292b8d6ba03b74622d41db8c5-1622013238", 
        "sha1": "a596f17ef736c4a181d36cc5ccbf564cd220f40d", 
        "resource": "07777bbc3ece5d962578c05ffef39764", 
        "response_code": 1, 
        "scan_date": "2021-05-26 07:13:58", 
        "permalink": "https://www.virustotal.com/gui/file/6d98cbeb6ef546278abd793a04d33f6a3ce2887292b8d6ba03b74622d41db8c5/detection/f-6d98cbeb6ef546278abd793a04d33f6a3ce2887292b8d6ba03b74622d41db8c5-1622013238", 
        "summary": {
            "positives": 0, 
            "permalink": "https://www.virustotal.com/gui/file/6d98cbeb6ef546278abd793a04d33f6a3ce2887292b8d6ba03b74622d41db8c5/detection/f-6d98cbeb6ef546278abd793a04d33f6a3ce2887292b8d6ba03b74622d41db8c5-1622013238", 
            "scan_date": "2021-05-26 07:13:58"
        }, 
        "sha256": "6d98cbeb6ef546278abd793a04d33f6a3ce2887292b8d6ba03b74622d41db8c5", 
        "normalized": [], 
        "total": 60, 
        "positives": 0, 
        "verbose_msg": "Scan finished, information embedded", 
        "md5": "07777bbc3ece5d962578c05ffef39764"
    }, 
    "network": {
        "udp": [], 
        "dns_servers": [], 
        "http": [], 
        "smtp": [], 
        "tcp": [], 
        "geoinfo": {}, 
        "mitm": [], 
        "https_ex": [], 
        "http_ex": [], 
        "sorted_pcap_sha256": "9a890ce43b667520c1013b00ad71b24cd768ebab302420ddeb7586b77cc4ea8d", 
        "icmp": [], 
        "tls": [], 
        "dead_hosts": [], 
        "smtp_ex": [], 
        "hosts": [], 
        "pcap_sha256": "937a9a621859033bcbc9b70d196298851135c6ac55a151c0c20f9a405c613366", 
        "dns": [], 
        "domains": [], 
        "irc": []
    }, 
    "resubmit": {
        "resubmit_ids": []
    }, 
    "snort": {
        "alerts": []
    }, 
    "memory": {
        "malconfscan": {
            "data": [], 
            "config": {
                "filter": false
            }
        }, 
        "yarascan": {
            "data": [
                {
                    "owner": "Process svchost.exe Pid 908", 
                    "hexdump": "0x0450c548  73 00 79 00 73 00 74 00 65 00 6d 00 69 00 6e 00   s.y.s.t.e.m.i.n.\n0x0450c558  66 00 6f 00 2e 00 65 00 78 00 65 00 00 00 00 00   f.o...e.x.e.....\n0x0450c568  07 f7 43 5c 42 00 00 80 36 02 50 04 00 00 00 00   ..C\\B...6.P.....\n0x0450c578  01 00 00 00 00 00 00 00 00 00 00 00 00 00 00 00   ................\n", 
                    "rule": "gen_memory_commands_shell_dev"
                }, 
                {
                    "owner": "Process explorer.exe Pid 1696", 
                    "hexdump": "0x07213128  73 00 79 00 73 00 74 00 65 00 6d 00 69 00 6e 00   s.y.s.t.e.m.i.n.\n0x07213138  66 00 6f 00 2e 00 65 00 78 00 65 00 00 00 00 00   f.o...e.x.e.....\n0x07213148  91 d0 2a 12 0c 00 00 80 52 05 21 07 00 00 00 00   ..*.....R.!.....\n0x07213158  01 00 00 00 00 00 00 00 00 00 00 00 00 00 00 00   ................\n", 
                    "rule": "gen_memory_commands_shell_dev"
                }
            ], 
            "config": {
                "filter": false
            }
        }
    }, 
    "debug": {
        "action": [], 
        "dbgview": [], 
        "errors": [], 
        "log": [
            "2021-08-04 21:58:37,015 [analyzer] DEBUG: Starting analyzer from: C:\\tmpsftntc\n", 
            "2021-08-04 21:58:37,015 [analyzer] DEBUG: Pipe server name: \\??\\PIPE\\udQjoScuLdYXBNBXbHPOc\n", 
            "2021-08-04 21:58:37,015 [analyzer] DEBUG: Log pipe server name: \\??\\PIPE\\qmzXSQIZiqbGkztaAx\n", 
            "2021-08-04 21:58:37,015 [analyzer] DEBUG: elf\n"
        ], 
        "cuckoo": [
            "2021-08-04 23:25:49,954 [cuckoo.core.scheduler] DEBUG: Task #2344785: no machine available yet\n", 
            "2021-08-04 23:26:00,024 [cuckoo.core.scheduler] INFO: Task #2344785: acquired machine win7x6421 (label=win7x6421)\n", 
            "2021-08-04 23:26:00,025 [cuckoo.core.resultserver] DEBUG: Now tracking machine 192.168.168.221 for task #2344785\n", 
            "2021-08-04 23:26:00,114 [cuckoo.auxiliary.sniffer] INFO: Started sniffer with PID 554742 (interface=vboxnet0, host=192.168.168.221)\n", 
            "2021-08-04 23:26:00,241 [cuckoo.machinery.virtualbox] DEBUG: Starting vm win7x6421\n", 
            "2021-08-04 23:26:00,628 [cuckoo.machinery.virtualbox] DEBUG: Restoring virtual machine win7x6421 to vmcloak\n", 
            "2021-08-04 23:29:01,482 [cuckoo.core.guest] INFO: Starting analysis #2344785 on guest (id=win7x6421, ip=192.168.168.221)\n", 
            "2021-08-04 23:29:02,487 [cuckoo.core.guest] DEBUG: win7x6421: not ready yet\n", 
            "2021-08-04 23:29:03,492 [cuckoo.core.guest] DEBUG: win7x6421: not ready yet\n", 
            "2021-08-04 23:29:04,498 [cuckoo.core.guest] DEBUG: win7x6421: not ready yet\n", 
            "2021-08-04 23:29:04,517 [cuckoo.core.guest] INFO: Guest is running Cuckoo Agent 0.10 (id=win7x6421, ip=192.168.168.221)\n", 
            "2021-08-04 23:29:04,591 [cuckoo.core.guest] DEBUG: Uploading analyzer to guest (id=win7x6421, ip=192.168.168.221, monitor=latest, size=6640384)\n", 
            "2021-08-04 23:29:05,720 [cuckoo.core.resultserver] DEBUG: Task #2344785: live log analysis.log initialized.\n", 
            "2021-08-04 23:29:05,801 [cuckoo.core.resultserver] DEBUG: Task #2344785 had connection reset for <Context for LOG>\n", 
            "2021-08-04 23:29:08,416 [cuckoo.core.guest] WARNING: win7x6421: analysis #2344785 caught an exception\n", 
            "Traceback (most recent call last):\n", 
            "  File \"C:/tmpsftntc/analyzer.py\", line 824, in <module>\n", 
            "    success = analyzer.run()\n", 
            "  File \"C:/tmpsftntc/analyzer.py\", line 593, in run\n", 
            "    \"not exist.\".format(package_name))\n", 
            "CuckooError: Unable to import package \"modules.packages.elf\", does not exist.\n", 
            "\n", 
            "2021-08-04 23:29:08,425 [cuckoo.core.plugins] DEBUG: Stopped auxiliary module: Redsocks\n", 
            "2021-08-04 23:29:08,506 [cuckoo.core.plugins] DEBUG: Stopped auxiliary module: Sniffer\n", 
            "2021-08-04 23:29:32,612 [cuckoo.machinery.virtualbox] INFO: Successfully generated memory dump for virtual machine with label win7x6421 to path /srv/cuckoo/cwd/storage/analyses/2344785/memory.dmp\n", 
            "2021-08-04 23:29:32,614 [cuckoo.machinery.virtualbox] DEBUG: Stopping vm win7x6421\n", 
            "2021-08-04 23:34:00,477 [cuckoo.core.resultserver] DEBUG: Stopped tracking machine 192.168.168.221 for task #2344785\n", 
            "2021-08-04 23:34:00,623 [cuckoo.core.scheduler] DEBUG: Released database task #2344785\n", 
            "2021-08-04 23:34:02,137 [cuckoo.core.scheduler] INFO: Task #2344785: analysis procedure completed\n"
        ]
    }, 
    "strings": [
        "/lib/ld-linux.so.2", 
        "libnetpbm.so.10", 
        "_ITM_deregisterTMCloneTable", 
        "__gmon_start__", 
        "_Jv_RegisterClasses", 
        "_ITM_registerTMCloneTable", 
        "ppm_writeppmrow", 
        "pm_keymatch", 
        "ppm_writeppminit", 
        "pm_error", 
        "ppm_init", 
        "pm_usage", 
        "pm_allocrow", 
        "pm_close", 
        "pm_openr", 
        "libc.so.6", 
        "_IO_stdin_used", 
        "strtol", 
        "stdout", 
        "_IO_getc", 
        "__libc_start_main", 
        "_edata", 
        "__bss_start", 
        "GLIBC_2.0", 
        "-headerskip", 
        "-rowskip", 
        "-interpixel", 
        "-interrow", 
        "EOF / read error", 
        "[-headerskip N] [-rowskip N] [-rgb|-rbg|-grb|-gbr|-brg|-bgr] [-interpixel|-interrow] <width> <height> [rawfile]", 
        ";*2$\",", 
        ".shstrtab", 
        ".interp", 
        ".note.ABI-tag", 
        ".note.gnu.build-id", 
        ".gnu.hash", 
        ".dynsym", 
        ".dynstr", 
        ".gnu.version", 
        ".gnu.version_r", 
        ".rel.dyn", 
        ".rel.plt", 
        ".plt.got", 
        ".rodata", 
        ".eh_frame_hdr", 
        ".eh_frame", 
        ".init_array", 
        ".fini_array", 
        ".dynamic", 
        ".got.plt"
    ], 
    "metadata": {
        "output": {
            "pcap": {
                "basename": "dump.pcap", 
                "sha256": "937a9a621859033bcbc9b70d196298851135c6ac55a151c0c20f9a405c613366", 
                "dirname": ""
            }
        }
    }
}